4-bits-counter/counter.v
module counter (
    input clk,          // Clock do sistema
    input rst_n,        // Reset ativo em nível baixo (padrão de mercado)
    output reg [3:0] out // Saída de 4 bits (0 a 15)
);

    // Lógica Sequencial: Acontece na borda de subida do clock
    always @(posedge clk or negedge rst_n) begin
        if (!rst_n) begin
            // Se o reset for 0 (pressionado), zera tudo
            out <= 4'b0000;
        end else begin
            // Senão, incrementa +1
            out <= out + 1;
        end
    end

endmodule

4-bits-counter/tb_counter.v
`timescale 1ns / 1ps // Define a unidade de tempo (1 nanossegundo)

module tb_counter;

    // Sinais para conectar no nosso módulo
    reg clk;
    reg rst_n;
    wire [3:0] out;

    // Instancia o nosso Design (DUT - Device Under Test)
    counter uut (
        .clk(clk),
        .rst_n(rst_n),
        .out(out)
    );

    // 1. Gerador de Clock (Isso simula o cristal oscilador da placa)
    initial begin
        clk = 0;
        forever #5 clk = ~clk; // Inverte o clock a cada 5ns (Período = 10ns)
    end

    // 2. O Roteiro do Teste
    initial begin
        // Configuração para gerar o arquivo de ondas para o GTKWave
        $dumpfile("waves.vcd"); // Nome do arquivo de saída
        $dumpvars(0, tb_counter); // Salvar todas as variáveis desse módulo

        // Cenário de Teste
        $display("Iniciando Simulação...");

        rst_n = 0; // Segura o reset apertado
        #20;       // Espera 20ns
        rst_n = 1; // Solta o reset (começa a contar)

        #200;      // Deixa rodar por 200ns (o contador vai subir)

        rst_n = 0; // Aperta o reset de novo pra ver se zera
        #20;
        rst_n = 1;

        #50;
        $display("Fim da Simulação.");
        $finish; // Encerra a simulação
    end

endmodule

4-bits-counter/waves.vcd
$date
	Tue Jan 13 11:39:01 2026
$end
$version
	Icarus Verilog
$end
$timescale
	1ps
$end
$scope module tb_counter $end
$var wire 4 ! out [3:0] $end
$var reg 1 " clk $end
$var reg 1 # rst_n $end
$scope module uut $end
$var wire 1 " clk $end
$var wire 1 # rst_n $end
$var reg 4 $ out [3:0] $end
$upscope $end
$upscope $end
$enddefinitions $end
$comment Show the parameter values. $end
$dumpall
$end
#0
$dumpvars
b0 $
0#
0"
b0 !
$end
#5000
1"
#10000
0"
#15000
1"
#20000
0"
1#
#25000
b1 !
b1 $
1"
#30000
0"
#35000
b10 !
b10 $
1"
#40000
0"
#45000
b11 !
b11 $
1"
#50000
0"
#55000
b100 !
b100 $
1"
#60000
0"
#65000
b101 !
b101 $
1"
#70000
0"
#75000
b110 !
b110 $
1"
#80000
0"
#85000
b111 !
b111 $
1"
#90000
0"
#95000
b1000 !
b1000 $
1"
#100000
0"
#105000
b1001 !
b1001 $
1"
#110000
0"
#115000
b1010 !
b1010 $
1"
#120000
0"
#125000
b1011 !
b1011 $
1"
#130000
0"
#135000
b1100 !
b1100 $
1"
#140000
0"
#145000
b1101 !
b1101 $
1"
#150000
0"
#155000
b1110 !
b1110 $
1"
#160000
0"
#165000
b1111 !
b1111 $
1"
#170000
0"
#175000
b0 !
b0 $
1"
#180000
0"
#185000
b1 !
b1 $
1"
#190000
0"
#195000
b10 !
b10 $
1"
#200000
0"
#205000
b11 !
b11 $
1"
#210000
0"
#215000
b100 !
b100 $
1"
#220000
b0 !
b0 $
0"
0#
#225000
1"
#230000
0"
#235000
1"
#240000
0"
1#
#245000
b1 !
b1 $
1"
#250000
0"
#255000
b10 !
b10 $
1"
#260000
0"
#265000
b11 !
b11 $
1"
#270000
0"
#275000
b100 !
b100 $
1"
#280000
0"
#285000
b101 !
b101 $
1"
