pwm/pwm.v
module pwm(
    // The "wire" keyword is optional for ports, but added here for clarity
    // The wire keyword indicates that these ports are connections rather than storage elements
    input wire clk,          // System clock
    input wire reset_n,        // Active-low reset
    // The duty cycle input (0-255 for 8-bit resolution)
    input wire [7:0] duty, // 8-bit duty cycle input (0-255)
    // The "reg" keyword means this port will hold its value until explicitly changed
    output reg pwm_out      // PWM output signal
);

reg [7:0] counter; // 8-bit counter register

always @(posedge clk or negedge reset_n) begin
    if (!reset_n) begin
        counter <= 8'b0; // Reset counter to 0 on reset
        pwm_out <= 1'b0; // Set PWM output low on reset
    end else begin
        counter <= counter + 1; // Increment counter on each clock cycle

        // Compare counter with duty cycle to set PWM output
        if (counter < duty) begin
            pwm_out <= 1'b1; // Set PWM output high if counter is less than duty
        end else begin
            pwm_out <= 1'b0; // Set PWM output low otherwise
        end
    end
end
endmodule

pwm/tb_pwm.v
module tb_pwm;
    reg clk;
    reg reset_n;
    reg [7:0] duty;
    // The "wire" keyword is used for signals that are driven by the DUT (Device Under Test)
    // This means we cannot assign values to them in the testbench
    // They will get their values from the pwm module
    wire pwm_out;

    // Instantiate our pwm module (DUT - Device Under Test)
    // We connect the signals defined above to the pwm ports
    // "uut" stands for "Unit Under Test"
    // The dot notation connects the module ports to the testbench signals
    pwm uut (
        .clk(clk),
        .reset_n(reset_n),
        .duty(duty),
        .pwm_out(pwm_out)
    );

    always begin
        clk = 0;
        #5; // Wait 5 time units
        clk = 1;
        #5; // Wait another 5 time units
    end
    
    always @(posedge pwm_out) begin
        $display("[Time %0t]: PWM output is HIGH", $time);
    end

    always @(negedge pwm_out) begin
        $display("[Time %0t]: PWM output is LOW", $time);
    end

    initial begin
        $dumpfile("waves.vcd"); // Output file name
        $dumpvars(0, tb_pwm); // Save all variables from this module
        
        $display("Starting PWM simulation...");
        // Initialize signals
        clk = 0;
        reset_n = 0; // Start with reset asserted
        #15;          // Wait 15 time units
        reset_n = 1; // Release reset

        // Set initial duty cycle
        duty = 8'd128; // Set duty cycle to 50%
        // Run the simulation for a certain period
        #3000;        // Let it run for 3000 time units

        // Change duty cycle to 75%
        duty = 8'd192;
        #3000;        // Let it run for another 3000 time units

        // Change duty cycle to 25%
        duty = 8'd64;
        #3000;        // Let it run for another 3000 time units
        
        $display("End of PWM simulation.");
        $finish; // End simulation
    end
endmodule

pwm/waves.vcd
$date
	Tue Jan 13 17:25:42 2026
$end
$version
	Icarus Verilog
$end
$timescale
	1s
$end
$scope module tb_pwm $end
$var wire 1 ! pwm_out $end
$var reg 1 " clk $end
$var reg 8 # duty [7:0] $end
$var reg 1 $ reset_n $end
$scope module uut $end
$var wire 1 " clk $end
$var wire 8 % duty [7:0] $end
$var wire 1 $ reset_n $end
$var reg 8 & counter [7:0] $end
$var reg 1 ! pwm_out $end
$upscope $end
$upscope $end
$enddefinitions $end
$comment Show the parameter values. $end
$dumpall
$end
#0
$dumpvars
b0 &
bx %
0$
bx #
0"
0!
$end
#5
1"
#10
0"
#15
1!
b1 &
1"
b10000000 #
b10000000 %
1$
#20
0"
#25
b10 &
1"
#30
0"
#35
b11 &
1"
#40
0"
#45
b100 &
1"
#50
0"
#55
b101 &
1"
#60
0"
#65
b110 &
1"
#70
0"
#75
b111 &
1"
#80
0"
#85
b1000 &
1"
#90
0"
#95
b1001 &
1"
#100
0"
#105
b1010 &
1"
#110
0"
#115
b1011 &
1"
#120
0"
#125
b1100 &
1"
#130
0"
#135
b1101 &
1"
#140
0"
#145
b1110 &
1"
#150
0"
#155
b1111 &
1"
#160
0"
#165
b10000 &
1"
#170
0"
#175
b10001 &
1"
#180
0"
#185
b10010 &
1"
#190
0"
#195
b10011 &
1"
#200
0"
#205
b10100 &
1"
#210
0"
#215
b10101 &
1"
#220
0"
#225
b10110 &
1"
#230
0"
#235
b10111 &
1"
#240
0"
#245
b11000 &
1"
#250
0"
#255
b11001 &
1"
#260
0"
#265
b11010 &
1"
#270
0"
#275
b11011 &
1"
#280
0"
#285
b11100 &
1"
#290
0"
#295
b11101 &
1"
#300
0"
#305
b11110 &
1"
#310
0"
#315
b11111 &
1"
#320
0"
#325
b100000 &
1"
#330
0"
#335
b100001 &
1"
#340
0"
#345
b100010 &
1"
#350
0"
#355
b100011 &
1"
#360
0"
#365
b100100 &
1"
#370
0"
#375
b100101 &
1"
#380
0"
#385
b100110 &
1"
#390
0"
#395
b100111 &
1"
#400
0"
#405
b101000 &
1"
#410
0"
#415
b101001 &
1"
#420
0"
#425
b101010 &
1"
#430
0"
#435
b101011 &
1"
#440
0"
#445
b101100 &
1"
#450
0"
#455
b101101 &
1"
#460
0"
#465
b101110 &
1"
#470
0"
#475
b101111 &
1"
#480
0"
#485
b110000 &
1"
#490
0"
#495
b110001 &
1"
#500
0"
#505
b110010 &
1"
#510
0"
#515
b110011 &
1"
#520
0"
#525
b110100 &
1"
#530
0"
#535
b110101 &
1"
#540
0"
#545
b110110 &
1"
#550
0"
#555
b110111 &
1"
#560
0"
#565
b111000 &
1"
#570
0"
#575
b111001 &
1"
#580
0"
#585
b111010 &
1"
#590
0"
#595
b111011 &
1"
#600
0"
#605
b111100 &
1"
#610
0"
#615
b111101 &
1"
#620
0"
#625
b111110 &
1"
#630
0"
#635
b111111 &
1"
#640
0"
#645
b1000000 &
1"
#650
0"
#655
b1000001 &
1"
#660
0"
#665
b1000010 &
1"
#670
0"
#675
b1000011 &
1"
#680
0"
#685
b1000100 &
1"
#690
0"
#695
b1000101 &
1"
#700
0"
#705
b1000110 &
1"
#710
0"
#715
b1000111 &
1"
#720
0"
#725
b1001000 &
1"
#730
0"
#735
b1001001 &
1"
#740
0"
#745
b1001010 &
1"
#750
0"
#755
b1001011 &
1"
#760
0"
#765
b1001100 &
1"
#770
0"
#775
b1001101 &
1"
#780
0"
#785
b1001110 &
1"
#790
0"
#795
b1001111 &
1"
#800
0"
#805
b1010000 &
1"
#810
0"
#815
b1010001 &
1"
#820
0"
#825
b1010010 &
1"
#830
0"
#835
b1010011 &
1"
#840
0"
#845
b1010100 &
1"
#850
0"
#855
b1010101 &
1"
#860
0"
#865
b1010110 &
1"
#870
0"
#875
b1010111 &
1"
#880
0"
#885
b1011000 &
1"
#890
0"
#895
b1011001 &
1"
#900
0"
#905
b1011010 &
1"
#910
0"
#915
b1011011 &
1"
#920
0"
#925
b1011100 &
1"
#930
0"
#935
b1011101 &
1"
#940
0"
#945
b1011110 &
1"
#950
0"
#955
b1011111 &
1"
#960
0"
#965
b1100000 &
1"
#970
0"
#975
b1100001 &
1"
#980
0"
#985
b1100010 &
1"
#990
0"
#995
b1100011 &
1"
#1000
0"
#1005
b1100100 &
1"
#1010
0"
#1015
b1100101 &
1"
#1020
0"
#1025
b1100110 &
1"
#1030
0"
#1035
b1100111 &
1"
#1040
0"
#1045
b1101000 &
1"
#1050
0"
#1055
b1101001 &
1"
#1060
0"
#1065
b1101010 &
1"
#1070
0"
#1075
b1101011 &
1"
#1080
0"
#1085
b1101100 &
1"
#1090
0"
#1095
b1101101 &
1"
#1100
0"
#1105
b1101110 &
1"
#1110
0"
#1115
b1101111 &
1"
#1120
0"
#1125
b1110000 &
1"
#1130
0"
#1135
b1110001 &
1"
#1140
0"
#1145
b1110010 &
1"
#1150
0"
#1155
b1110011 &
1"
#1160
0"
#1165
b1110100 &
1"
#1170
0"
#1175
b1110101 &
1"
#1180
0"
#1185
b1110110 &
1"
#1190
0"
#1195
b1110111 &
1"
#1200
0"
#1205
b1111000 &
1"
#1210
0"
#1215
b1111001 &
1"
#1220
0"
#1225
b1111010 &
1"
#1230
0"
#1235
b1111011 &
1"
#1240
0"
#1245
b1111100 &
1"
#1250
0"
#1255
b1111101 &
1"
#1260
0"
#1265
b1111110 &
1"
#1270
0"
#1275
b1111111 &
1"
#1280
0"
#1285
b10000000 &
1"
#1290
0"
#1295
0!
b10000001 &
1"
#1300
0"
#1305
b10000010 &
1"
#1310
0"
#1315
b10000011 &
1"
#1320
0"
#1325
b10000100 &
1"
#1330
0"
#1335
b10000101 &
1"
#1340
0"
#1345
b10000110 &
1"
#1350
0"
#1355
b10000111 &
1"
#1360
0"
#1365
b10001000 &
1"
#1370
0"
#1375
b10001001 &
1"
#1380
0"
#1385
b10001010 &
1"
#1390
0"
#1395
b10001011 &
1"
#1400
0"
#1405
b10001100 &
1"
#1410
0"
#1415
b10001101 &
1"
#1420
0"
#1425
b10001110 &
1"
#1430
0"
#1435
b10001111 &
1"
#1440
0"
#1445
b10010000 &
1"
#1450
0"
#1455
b10010001 &
1"
#1460
0"
#1465
b10010010 &
1"
#1470
0"
#1475
b10010011 &
1"
#1480
0"
#1485
b10010100 &
1"
#1490
0"
#1495
b10010101 &
1"
#1500
0"
#1505
b10010110 &
1"
#1510
0"
#1515
b10010111 &
1"
#1520
0"
#1525
b10011000 &
1"
#1530
0"
#1535
b10011001 &
1"
#1540
0"
#1545
b10011010 &
1"
#1550
0"
#1555
b10011011 &
1"
#1560
0"
#1565
b10011100 &
1"
#1570
0"
#1575
b10011101 &
1"
#1580
0"
#1585
b10011110 &
1"
#1590
0"
#1595
b10011111 &
1"
#1600
0"
#1605
b10100000 &
1"
#1610
0"
#1615
b10100001 &
1"
#1620
0"
#1625
b10100010 &
1"
#1630
0"
#1635
b10100011 &
1"
#1640
0"
#1645
b10100100 &
1"
#1650
0"
#1655
b10100101 &
1"
#1660
0"
#1665
b10100110 &
1"
#1670
0"
#1675
b10100111 &
1"
#1680
0"
#1685
b10101000 &
1"
#1690
0"
#1695
b10101001 &
1"
#1700
0"
#1705
b10101010 &
1"
#1710
0"
#1715
b10101011 &
1"
#1720
0"
#1725
b10101100 &
1"
#1730
0"
#1735
b10101101 &
1"
#1740
0"
#1745
b10101110 &
1"
#1750
0"
#1755
b10101111 &
1"
#1760
0"
#1765
b10110000 &
1"
#1770
0"
#1775
b10110001 &
1"
#1780
0"
#1785
b10110010 &
1"
#1790
0"
#1795
b10110011 &
1"
#1800
0"
#1805
b10110100 &
1"
#1810
0"
#1815
b10110101 &
1"
#1820
0"
#1825
b10110110 &
1"
#1830
0"
#1835
b10110111 &
1"
#1840
0"
#1845
b10111000 &
1"
#1850
0"
#1855
b10111001 &
1"
#1860
0"
#1865
b10111010 &
1"
#1870
0"
#1875
b10111011 &
1"
#1880
0"
#1885
b10111100 &
1"
#1890
0"
#1895
b10111101 &
1"
#1900
0"
#1905
b10111110 &
1"
#1910
0"
#1915
b10111111 &
1"
#1920
0"
#1925
b11000000 &
1"
#1930
0"
#1935
b11000001 &
1"
#1940
0"
#1945
b11000010 &
1"
#1950
0"
#1955
b11000011 &
1"
#1960
0"
#1965
b11000100 &
1"
#1970
0"
#1975
b11000101 &
1"
#1980
0"
#1985
b11000110 &
1"
#1990
0"
#1995
b11000111 &
1"
#2000
0"
#2005
b11001000 &
1"
#2010
0"
#2015
b11001001 &
1"
#2020
0"
#2025
b11001010 &
1"
#2030
0"
#2035
b11001011 &
1"
#2040
0"
#2045
b11001100 &
1"
#2050
0"
#2055
b11001101 &
1"
#2060
0"
#2065
b11001110 &
1"
#2070
0"
#2075
b11001111 &
1"
#2080
0"
#2085
b11010000 &
1"
#2090
0"
#2095
b11010001 &
1"
#2100
0"
#2105
b11010010 &
1"
#2110
0"
#2115
b11010011 &
1"
#2120
0"
#2125
b11010100 &
1"
#2130
0"
#2135
b11010101 &
1"
#2140
0"
#2145
b11010110 &
1"
#2150
0"
#2155
b11010111 &
1"
#2160
0"
#2165
b11011000 &
1"
#2170
0"
#2175
b11011001 &
1"
#2180
0"
#2185
b11011010 &
1"
#2190
0"
#2195
b11011011 &
1"
#2200
0"
#2205
b11011100 &
1"
#2210
0"
#2215
b11011101 &
1"
#2220
0"
#2225
b11011110 &
1"
#2230
0"
#2235
b11011111 &
1"
#2240
0"
#2245
b11100000 &
1"
#2250
0"
#2255
b11100001 &
1"
#2260
0"
#2265
b11100010 &
1"
#2270
0"
#2275
b11100011 &
1"
#2280
0"
#2285
b11100100 &
1"
#2290
0"
#2295
b11100101 &
1"
#2300
0"
#2305
b11100110 &
1"
#2310
0"
#2315
b11100111 &
1"
#2320
0"
#2325
b11101000 &
1"
#2330
0"
#2335
b11101001 &
1"
#2340
0"
#2345
b11101010 &
1"
#2350
0"
#2355
b11101011 &
1"
#2360
0"
#2365
b11101100 &
1"
#2370
0"
#2375
b11101101 &
1"
#2380
0"
#2385
b11101110 &
1"
#2390
0"
#2395
b11101111 &
1"
#2400
0"
#2405
b11110000 &
1"
#2410
0"
#2415
b11110001 &
1"
#2420
0"
#2425
b11110010 &
1"
#2430
0"
#2435
b11110011 &
1"
#2440
0"
#2445
b11110100 &
1"
#2450
0"
#2455
b11110101 &
1"
#2460
0"
#2465
b11110110 &
1"
#2470
0"
#2475
b11110111 &
1"
#2480
0"
#2485
b11111000 &
1"
#2490
0"
#2495
b11111001 &
1"
#2500
0"
#2505
b11111010 &
1"
#2510
0"
#2515
b11111011 &
1"
#2520
0"
#2525
b11111100 &
1"
#2530
0"
#2535
b11111101 &
1"
#2540
0"
#2545
b11111110 &
1"
#2550
0"
#2555
b11111111 &
1"
#2560
0"
#2565
b0 &
1"
#2570
0"
#2575
1!
b1 &
1"
#2580
0"
#2585
b10 &
1"
#2590
0"
#2595
b11 &
1"
#2600
0"
#2605
b100 &
1"
#2610
0"
#2615
b101 &
1"
#2620
0"
#2625
b110 &
1"
#2630
0"
#2635
b111 &
1"
#2640
0"
#2645
b1000 &
1"
#2650
0"
#2655
b1001 &
1"
#2660
0"
#2665
b1010 &
1"
#2670
0"
#2675
b1011 &
1"
#2680
0"
#2685
b1100 &
1"
#2690
0"
#2695
b1101 &
1"
#2700
0"
#2705
b1110 &
1"
#2710
0"
#2715
b1111 &
1"
#2720
0"
#2725
b10000 &
1"
#2730
0"
#2735
b10001 &
1"
#2740
0"
#2745
b10010 &
1"
#2750
0"
#2755
b10011 &
1"
#2760
0"
#2765
b10100 &
1"
#2770
0"
#2775
b10101 &
1"
#2780
0"
#2785
b10110 &
1"
#2790
0"
#2795
b10111 &
1"
#2800
0"
#2805
b11000 &
1"
#2810
0"
#2815
b11001 &
1"
#2820
0"
#2825
b11010 &
1"
#2830
0"
#2835
b11011 &
1"
#2840
0"
#2845
b11100 &
1"
#2850
0"
#2855
b11101 &
1"
#2860
0"
#2865
b11110 &
1"
#2870
0"
#2875
b11111 &
1"
#2880
0"
#2885
b100000 &
1"
#2890
0"
#2895
b100001 &
1"
#2900
0"
#2905
b100010 &
1"
#2910
0"
#2915
b100011 &
1"
#2920
0"
#2925
b100100 &
1"
#2930
0"
#2935
b100101 &
1"
#2940
0"
#2945
b100110 &
1"
#2950
0"
#2955
b100111 &
1"
#2960
0"
#2965
b101000 &
1"
#2970
0"
#2975
b101001 &
1"
#2980
0"
#2985
b101010 &
1"
#2990
0"
#2995
b101011 &
1"
#3000
0"
#3005
b101100 &
1"
#3010
0"
#3015
b101101 &
1"
b11000000 #
b11000000 %
#3020
0"
#3025
b101110 &
1"
#3030
0"
#3035
b101111 &
1"
#3040
0"
#3045
b110000 &
1"
#3050
0"
#3055
b110001 &
1"
#3060
0"
#3065
b110010 &
1"
#3070
0"
#3075
b110011 &
1"
#3080
0"
#3085
b110100 &
1"
#3090
0"
#3095
b110101 &
1"
#3100
0"
#3105
b110110 &
1"
#3110
0"
#3115
b110111 &
1"
#3120
0"
#3125
b111000 &
1"
#3130
0"
#3135
b111001 &
1"
#3140
0"
#3145
b111010 &
1"
#3150
0"
#3155
b111011 &
1"
#3160
0"
#3165
b111100 &
1"
#3170
0"
#3175
b111101 &
1"
#3180
0"
#3185
b111110 &
1"
#3190
0"
#3195
b111111 &
1"
#3200
0"
#3205
b1000000 &
1"
#3210
0"
#3215
b1000001 &
1"
#3220
0"
#3225
b1000010 &
1"
#3230
0"
#3235
b1000011 &
1"
#3240
0"
#3245
b1000100 &
1"
#3250
0"
#3255
b1000101 &
1"
#3260
0"
#3265
b1000110 &
1"
#3270
0"
#3275
b1000111 &
1"
#3280
0"
#3285
b1001000 &
1"
#3290
0"
#3295
b1001001 &
1"
#3300
0"
#3305
b1001010 &
1"
#3310
0"
#3315
b1001011 &
1"
#3320
0"
#3325
b1001100 &
1"
#3330
0"
#3335
b1001101 &
1"
#3340
0"
#3345
b1001110 &
1"
#3350
0"
#3355
b1001111 &
1"
#3360
0"
#3365
b1010000 &
1"
#3370
0"
#3375
b1010001 &
1"
#3380
0"
#3385
b1010010 &
1"
#3390
0"
#3395
b1010011 &
1"
#3400
0"
#3405
b1010100 &
1"
#3410
0"
#3415
b1010101 &
1"
#3420
0"
#3425
b1010110 &
1"
#3430
0"
#3435
b1010111 &
1"
#3440
0"
#3445
b1011000 &
1"
#3450
0"
#3455
b1011001 &
1"
#3460
0"
#3465
b1011010 &
1"
#3470
0"
#3475
b1011011 &
1"
#3480
0"
#3485
b1011100 &
1"
#3490
0"
#3495
b1011101 &
1"
#3500
0"
#3505
b1011110 &
1"
#3510
0"
#3515
b1011111 &
1"
#3520
0"
#3525
b1100000 &
1"
#3530
0"
#3535
b1100001 &
1"
#3540
0"
#3545
b1100010 &
1"
#3550
0"
#3555
b1100011 &
1"
#3560
0"
#3565
b1100100 &
1"
#3570
0"
#3575
b1100101 &
1"
#3580
0"
#3585
b1100110 &
1"
#3590
0"
#3595
b1100111 &
1"
#3600
0"
#3605
b1101000 &
1"
#3610
0"
#3615
b1101001 &
1"
#3620
0"
#3625
b1101010 &
1"
#3630
0"
#3635
b1101011 &
1"
#3640
0"
#3645
b1101100 &
1"
#3650
0"
#3655
b1101101 &
1"
#3660
0"
#3665
b1101110 &
1"
#3670
0"
#3675
b1101111 &
1"
#3680
0"
#3685
b1110000 &
1"
#3690
0"
#3695
b1110001 &
1"
#3700
0"
#3705
b1110010 &
1"
#3710
0"
#3715
b1110011 &
1"
#3720
0"
#3725
b1110100 &
1"
#3730
0"
#3735
b1110101 &
1"
#3740
0"
#3745
b1110110 &
1"
#3750
0"
#3755
b1110111 &
1"
#3760
0"
#3765
b1111000 &
1"
#3770
0"
#3775
b1111001 &
1"
#3780
0"
#3785
b1111010 &
1"
#3790
0"
#3795
b1111011 &
1"
#3800
0"
#3805
b1111100 &
1"
#3810
0"
#3815
b1111101 &
1"
#3820
0"
#3825
b1111110 &
1"
#3830
0"
#3835
b1111111 &
1"
#3840
0"
#3845
b10000000 &
1"
#3850
0"
#3855
b10000001 &
1"
#3860
0"
#3865
b10000010 &
1"
#3870
0"
#3875
b10000011 &
1"
#3880
0"
#3885
b10000100 &
1"
#3890
0"
#3895
b10000101 &
1"
#3900
0"
#3905
b10000110 &
1"
#3910
0"
#3915
b10000111 &
1"
#3920
0"
#3925
b10001000 &
1"
#3930
0"
#3935
b10001001 &
1"
#3940
0"
#3945
b10001010 &
1"
#3950
0"
#3955
b10001011 &
1"
#3960
0"
#3965
b10001100 &
1"
#3970
0"
#3975
b10001101 &
1"
#3980
0"
#3985
b10001110 &
1"
#3990
0"
#3995
b10001111 &
1"
#4000
0"
#4005
b10010000 &
1"
#4010
0"
#4015
b10010001 &
1"
#4020
0"
#4025
b10010010 &
1"
#4030
0"
#4035
b10010011 &
1"
#4040
0"
#4045
b10010100 &
1"
#4050
0"
#4055
b10010101 &
1"
#4060
0"
#4065
b10010110 &
1"
#4070
0"
#4075
b10010111 &
1"
#4080
0"
#4085
b10011000 &
1"
#4090
0"
#4095
b10011001 &
1"
#4100
0"
#4105
b10011010 &
1"
#4110
0"
#4115
b10011011 &
1"
#4120
0"
#4125
b10011100 &
1"
#4130
0"
#4135
b10011101 &
1"
#4140
0"
#4145
b10011110 &
1"
#4150
0"
#4155
b10011111 &
1"
#4160
0"
#4165
b10100000 &
1"
#4170
0"
#4175
b10100001 &
1"
#4180
0"
#4185
b10100010 &
1"
#4190
0"
#4195
b10100011 &
1"
#4200
0"
#4205
b10100100 &
1"
#4210
0"
#4215
b10100101 &
1"
#4220
0"
#4225
b10100110 &
1"
#4230
0"
#4235
b10100111 &
1"
#4240
0"
#4245
b10101000 &
1"
#4250
0"
#4255
b10101001 &
1"
#4260
0"
#4265
b10101010 &
1"
#4270
0"
#4275
b10101011 &
1"
#4280
0"
#4285
b10101100 &
1"
#4290
0"
#4295
b10101101 &
1"
#4300
0"
#4305
b10101110 &
1"
#4310
0"
#4315
b10101111 &
1"
#4320
0"
#4325
b10110000 &
1"
#4330
0"
#4335
b10110001 &
1"
#4340
0"
#4345
b10110010 &
1"
#4350
0"
#4355
b10110011 &
1"
#4360
0"
#4365
b10110100 &
1"
#4370
0"
#4375
b10110101 &
1"
#4380
0"
#4385
b10110110 &
1"
#4390
0"
#4395
b10110111 &
1"
#4400
0"
#4405
b10111000 &
1"
#4410
0"
#4415
b10111001 &
1"
#4420
0"
#4425
b10111010 &
1"
#4430
0"
#4435
b10111011 &
1"
#4440
0"
#4445
b10111100 &
1"
#4450
0"
#4455
b10111101 &
1"
#4460
0"
#4465
b10111110 &
1"
#4470
0"
#4475
b10111111 &
1"
#4480
0"
#4485
b11000000 &
1"
#4490
0"
#4495
0!
b11000001 &
1"
#4500
0"
#4505
b11000010 &
1"
#4510
0"
#4515
b11000011 &
1"
#4520
0"
#4525
b11000100 &
1"
#4530
0"
#4535
b11000101 &
1"
#4540
0"
#4545
b11000110 &
1"
#4550
0"
#4555
b11000111 &
1"
#4560
0"
#4565
b11001000 &
1"
#4570
0"
#4575
b11001001 &
1"
#4580
0"
#4585
b11001010 &
1"
#4590
0"
#4595
b11001011 &
1"
#4600
0"
#4605
b11001100 &
1"
#4610
0"
#4615
b11001101 &
1"
#4620
0"
#4625
b11001110 &
1"
#4630
0"
#4635
b11001111 &
1"
#4640
0"
#4645
b11010000 &
1"
#4650
0"
#4655
b11010001 &
1"
#4660
0"
#4665
b11010010 &
1"
#4670
0"
#4675
b11010011 &
1"
#4680
0"
#4685
b11010100 &
1"
#4690
0"
#4695
b11010101 &
1"
#4700
0"
#4705
b11010110 &
1"
#4710
0"
#4715
b11010111 &
1"
#4720
0"
#4725
b11011000 &
1"
#4730
0"
#4735
b11011001 &
1"
#4740
0"
#4745
b11011010 &
1"
#4750
0"
#4755
b11011011 &
1"
#4760
0"
#4765
b11011100 &
1"
#4770
0"
#4775
b11011101 &
1"
#4780
0"
#4785
b11011110 &
1"
#4790
0"
#4795
b11011111 &
1"
#4800
0"
#4805
b11100000 &
1"
#4810
0"
#4815
b11100001 &
1"
#4820
0"
#4825
b11100010 &
1"
#4830
0"
#4835
b11100011 &
1"
#4840
0"
#4845
b11100100 &
1"
#4850
0"
#4855
b11100101 &
1"
#4860
0"
#4865
b11100110 &
1"
#4870
0"
#4875
b11100111 &
1"
#4880
0"
#4885
b11101000 &
1"
#4890
0"
#4895
b11101001 &
1"
#4900
0"
#4905
b11101010 &
1"
#4910
0"
#4915
b11101011 &
1"
#4920
0"
#4925
b11101100 &
1"
#4930
0"
#4935
b11101101 &
1"
#4940
0"
#4945
b11101110 &
1"
#4950
0"
#4955
b11101111 &
1"
#4960
0"
#4965
b11110000 &
1"
#4970
0"
#4975
b11110001 &
1"
#4980
0"
#4985
b11110010 &
1"
#4990
0"
#4995
b11110011 &
1"
#5000
0"
#5005
b11110100 &
1"
#5010
0"
#5015
b11110101 &
1"
#5020
0"
#5025
b11110110 &
1"
#5030
0"
#5035
b11110111 &
1"
#5040
0"
#5045
b11111000 &
1"
#5050
0"
#5055
b11111001 &
1"
#5060
0"
#5065
b11111010 &
1"
#5070
0"
#5075
b11111011 &
1"
#5080
0"
#5085
b11111100 &
1"
#5090
0"
#5095
b11111101 &
1"
#5100
0"
#5105
b11111110 &
1"
#5110
0"
#5115
b11111111 &
1"
#5120
0"
#5125
b0 &
1"
#5130
0"
#5135
1!
b1 &
1"
#5140
0"
#5145
b10 &
1"
#5150
0"
#5155
b11 &
1"
#5160
0"
#5165
b100 &
1"
#5170
0"
#5175
b101 &
1"
#5180
0"
#5185
b110 &
1"
#5190
0"
#5195
b111 &
1"
#5200
0"
#5205
b1000 &
1"
#5210
0"
#5215
b1001 &
1"
#5220
0"
#5225
b1010 &
1"
#5230
0"
#5235
b1011 &
1"
#5240
0"
#5245
b1100 &
1"
#5250
0"
#5255
b1101 &
1"
#5260
0"
#5265
b1110 &
1"
#5270
0"
#5275
b1111 &
1"
#5280
0"
#5285
b10000 &
1"
#5290
0"
#5295
b10001 &
1"
#5300
0"
#5305
b10010 &
1"
#5310
0"
#5315
b10011 &
1"
#5320
0"
#5325
b10100 &
1"
#5330
0"
#5335
b10101 &
1"
#5340
0"
#5345
b10110 &
1"
#5350
0"
#5355
b10111 &
1"
#5360
0"
#5365
b11000 &
1"
#5370
0"
#5375
b11001 &
1"
#5380
0"
#5385
b11010 &
1"
#5390
0"
#5395
b11011 &
1"
#5400
0"
#5405
b11100 &
1"
#5410
0"
#5415
b11101 &
1"
#5420
0"
#5425
b11110 &
1"
#5430
0"
#5435
b11111 &
1"
#5440
0"
#5445
b100000 &
1"
#5450
0"
#5455
b100001 &
1"
#5460
0"
#5465
b100010 &
1"
#5470
0"
#5475
b100011 &
1"
#5480
0"
#5485
b100100 &
1"
#5490
0"
#5495
b100101 &
1"
#5500
0"
#5505
b100110 &
1"
#5510
0"
#5515
b100111 &
1"
#5520
0"
#5525
b101000 &
1"
#5530
0"
#5535
b101001 &
1"
#5540
0"
#5545
b101010 &
1"
#5550
0"
#5555
b101011 &
1"
#5560
0"
#5565
b101100 &
1"
#5570
0"
#5575
b101101 &
1"
#5580
0"
#5585
b101110 &
1"
#5590
0"
#5595
b101111 &
1"
#5600
0"
#5605
b110000 &
1"
#5610
0"
#5615
b110001 &
1"
#5620
0"
#5625
b110010 &
1"
#5630
0"
#5635
b110011 &
1"
#5640
0"
#5645
b110100 &
1"
#5650
0"
#5655
b110101 &
1"
#5660
0"
#5665
b110110 &
1"
#5670
0"
#5675
b110111 &
1"
#5680
0"
#5685
b111000 &
1"
#5690
0"
#5695
b111001 &
1"
#5700
0"
#5705
b111010 &
1"
#5710
0"
#5715
b111011 &
1"
#5720
0"
#5725
b111100 &
1"
#5730
0"
#5735
b111101 &
1"
#5740
0"
#5745
b111110 &
1"
#5750
0"
#5755
b111111 &
1"
#5760
0"
#5765
b1000000 &
1"
#5770
0"
#5775
b1000001 &
1"
#5780
0"
#5785
b1000010 &
1"
#5790
0"
#5795
b1000011 &
1"
#5800
0"
#5805
b1000100 &
1"
#5810
0"
#5815
b1000101 &
1"
#5820
0"
#5825
b1000110 &
1"
#5830
0"
#5835
b1000111 &
1"
#5840
0"
#5845
b1001000 &
1"
#5850
0"
#5855
b1001001 &
1"
#5860
0"
#5865
b1001010 &
1"
#5870
0"
#5875
b1001011 &
1"
#5880
0"
#5885
b1001100 &
1"
#5890
0"
#5895
b1001101 &
1"
#5900
0"
#5905
b1001110 &
1"
#5910
0"
#5915
b1001111 &
1"
#5920
0"
#5925
b1010000 &
1"
#5930
0"
#5935
b1010001 &
1"
#5940
0"
#5945
b1010010 &
1"
#5950
0"
#5955
b1010011 &
1"
#5960
0"
#5965
b1010100 &
1"
#5970
0"
#5975
b1010101 &
1"
#5980
0"
#5985
b1010110 &
1"
#5990
0"
#5995
b1010111 &
1"
#6000
0"
#6005
b1011000 &
1"
#6010
0"
#6015
0!
b1011001 &
1"
b1000000 #
b1000000 %
#6020
0"
#6025
b1011010 &
1"
#6030
0"
#6035
b1011011 &
1"
#6040
0"
#6045
b1011100 &
1"
#6050
0"
#6055
b1011101 &
1"
#6060
0"
#6065
b1011110 &
1"
#6070
0"
#6075
b1011111 &
1"
#6080
0"
#6085
b1100000 &
1"
#6090
0"
#6095
b1100001 &
1"
#6100
0"
#6105
b1100010 &
1"
#6110
0"
#6115
b1100011 &
1"
#6120
0"
#6125
b1100100 &
1"
#6130
0"
#6135
b1100101 &
1"
#6140
0"
#6145
b1100110 &
1"
#6150
0"
#6155
b1100111 &
1"
#6160
0"
#6165
b1101000 &
1"
#6170
0"
#6175
b1101001 &
1"
#6180
0"
#6185
b1101010 &
1"
#6190
0"
#6195
b1101011 &
1"
#6200
0"
#6205
b1101100 &
1"
#6210
0"
#6215
b1101101 &
1"
#6220
0"
#6225
b1101110 &
1"
#6230
0"
#6235
b1101111 &
1"
#6240
0"
#6245
b1110000 &
1"
#6250
0"
#6255
b1110001 &
1"
#6260
0"
#6265
b1110010 &
1"
#6270
0"
#6275
b1110011 &
1"
#6280
0"
#6285
b1110100 &
1"
#6290
0"
#6295
b1110101 &
1"
#6300
0"
#6305
b1110110 &
1"
#6310
0"
#6315
b1110111 &
1"
#6320
0"
#6325
b1111000 &
1"
#6330
0"
#6335
b1111001 &
1"
#6340
0"
#6345
b1111010 &
1"
#6350
0"
#6355
b1111011 &
1"
#6360
0"
#6365
b1111100 &
1"
#6370
0"
#6375
b1111101 &
1"
#6380
0"
#6385
b1111110 &
1"
#6390
0"
#6395
b1111111 &
1"
#6400
0"
#6405
b10000000 &
1"
#6410
0"
#6415
b10000001 &
1"
#6420
0"
#6425
b10000010 &
1"
#6430
0"
#6435
b10000011 &
1"
#6440
0"
#6445
b10000100 &
1"
#6450
0"
#6455
b10000101 &
1"
#6460
0"
#6465
b10000110 &
1"
#6470
0"
#6475
b10000111 &
1"
#6480
0"
#6485
b10001000 &
1"
#6490
0"
#6495
b10001001 &
1"
#6500
0"
#6505
b10001010 &
1"
#6510
0"
#6515
b10001011 &
1"
#6520
0"
#6525
b10001100 &
1"
#6530
0"
#6535
b10001101 &
1"
#6540
0"
#6545
b10001110 &
1"
#6550
0"
#6555
b10001111 &
1"
#6560
0"
#6565
b10010000 &
1"
#6570
0"
#6575
b10010001 &
1"
#6580
0"
#6585
b10010010 &
1"
#6590
0"
#6595
b10010011 &
1"
