alu-calculator/alu.v
// First we define the ALU module with inputs and outputs
module alu (
    // We need think, what are the inputs and outputs of an ALU
    // So, we have two operands (A and B), an operation selector as input
    // The "[3:0]" means it's a 4-bit wide bus
    input [3:0] A, // First operand
    input [3:0] B, // Second operand
    input [2:0] operation, // ALU operation select
    // And the result as output
    // The "reg" keyword is needed because we will assign value in an always block
    output reg [3:0] result // ALU result
);

    // Combinational logic: always block triggered on any input change
    // The "*" means "any input signal"
    always @(*) begin 
        // Case statement to select operation based on the operation input
        case (operation)
            // The "3" means it's a 3-bit wide bus
            // The "b" means binary
            // The "000" is the binary value for 0
            // The "001" is the binary value for 1 and so on...
            3'b000: result = A + B;        // Addition
            3'b001: result = A - B;        // Subtraction
            3'b010: result = A & B;        // AND
            3'b011: result = A | B;        // OR
            3'b100: result = A ^ B;        // XOR
            3'b101: result = ~A;           // NOT A
            // Here we add the "4" before the "b" to indicate a 4-bit binary value
            // Because the result is 4 bits wide
            3'b110: result = (A < B) ? 4'b0001 : 4'b0000; // Less than
            3'b111: result = 4'b0000;      // NOP (No operation)
            // If none of the above cases match, we set result to 0
            default: result = 4'b0000;     // Default case
        endcase
    end
endmodule

alu-calculator/tb_alu.v
// First we define the testbench module for the ALU
module tb_alu;
    // Signals to connect to our ALU module
    // The "reg" keyword is used for signals that will be driven in initial or always blocks
    // This means we can assign values to them in the testbench
    reg [3:0] A, B;
    reg [2:0] operation;
    // The "wire" keyword is used for signals that are driven by the DUT (Device Under Test)
    // This means we cannot assign values to them in the testbench
    // They will get their values from the ALU module
    wire [3:0] result;

    // Instantiate our ALU module (DUT - Device Under Test)
    // We connect the signals defined above to the ALU ports
    // "uut" stands for "Unit Under Test"
    // The dot notation connects the module ports to the testbench signals
    alu uut (
        .A(A),
        .B(B),
        .operation(operation),
        .result(result)
    );

    // Clock generator is not needed for combinational ALU
    // Test script
    // "initial" block runs once at the start of the simulation
    initial begin 
        // "dumpfile" specifies the output file for waveform data
        $dumpfile("waves.vcd"); // Output file name
        // "dumpvars" specifies which variables to record in the waveform
        $dumpvars(0, tb_alu); // Save all variables from this module

        // Test scenario
        $display("Starting ALU simulation...");

        // Testing addition
        A = 4'b0011; // 3
        B = 4'b0101; // 5
        operation = 3'b000; // Addition
        // Wait for some time to observe the result
        // The time unit depends on the `timescale` directive (default is 1ns)
        #10; // Wait 10 time units
        // The "display" command prints to the console
        // We print the inputs and the result
        // "%d" formats the number as decimal
        $display("A=%d, B=%d, operation=ADD, result=%d", A, B, result);

        // Testing subtraction
        operation = 3'b001; // Subtraction
        #10;
        $display("A=%d, B=%d, operation=SUB, result=%d", A, B, result);

        // Testing AND
        operation = 3'b010; // AND
        #10;
        $display("A=%d, B=%d, operation=AND, result=%d", A, B, result);

        // Testing OR
        operation = 3'b011; // OR
        #10;
        $display("A=%d, B=%d, operation=OR, result=%d", A, B, result);

        // Testing XOR
        operation = 3'b100; // XOR
        #10;
        $display("A=%d, B=%d, operation=XOR, result=%d", A, B, result);

        // Testing NOT A
        operation = 3'b101; // NOT A
        #10;
        $display("A=%d, operation=NOT A, result=%d", A, result);

        // Testing Less than
        operation = 3'b110; // Less than
        #10;
        $display("A=%d, B=%d, operation=LT, result=%d", A, B, result);

        // Testing NOP
        operation = 3'b111; // NOP
        #10;
        $display("A=%d, B=%d, operation=NOP, result=%d", A, B, result);

        $display("End of ALU simulation.");
        $finish; // End simulation
    end
endmodule

alu-calculator/waves.vcd
$date
	Tue Jan 13 15:58:55 2026
$end
$version
	Icarus Verilog
$end
$timescale
	1s
$end
$scope module tb_alu $end
$var wire 4 ! result [3:0] $end
$var reg 4 " A [3:0] $end
$var reg 4 # B [3:0] $end
$var reg 3 $ operation [2:0] $end
$scope module uut $end
$var wire 4 % A [3:0] $end
$var wire 4 & B [3:0] $end
$var wire 3 ' operation [2:0] $end
$var reg 4 ( result [3:0] $end
$upscope $end
$upscope $end
$enddefinitions $end
$comment Show the parameter values. $end
$dumpall
$end
#0
$dumpvars
b1000 (
b0 '
b101 &
b11 %
b0 $
b101 #
b11 "
b1000 !
$end
#10
b1110 !
b1110 (
b1 $
b1 '
#20
b1 !
b1 (
b10 $
b10 '
#30
b111 !
b111 (
b11 $
b11 '
#40
b110 !
b110 (
b100 $
b100 '
#50
b1100 !
b1100 (
b101 $
b101 '
#60
b1 !
b1 (
b110 $
b110 '
#70
b0 !
b0 (
b111 $
b111 '
