traffic_light/traffic_light.v
module traffic_light(
    // The clock is used to time the light changes
    input clk, // System clock
    // The reset is used to initialize the state machine
    input reset_n, // Active-low reset
    // Outputs for the traffic light colors
    output red, // Red light output
    output yellow, // Yellow light output
    output green // Green light output
);

// State encoding
// The "parameter" keyword defines constants
// Each state is represented by a 2-bit value
parameter RED_STATE = 2'b00; // Red state = binary 00
parameter GREEN_STATE = 2'b01; // Green state = binary 01
parameter YELLOW_STATE = 2'b10; // Yellow state = binary 10

// State register to hold the current state
reg [1:0] state; // Current state register
reg [5:0] timer; // Timer register for state duration

// Sequential logic: State transition on clock edge or reset
// The state machine changes state on the rising edge of the clock
// or resets to the initial state when reset is asserted
// The "always" block defines a process that runs on specific events
// Here, it triggers on the rising edge of clk or the falling edge of reset_n
// The "posedge" keyword indicates a rising edge, and "negedge" indicates a falling edge
// This means the block will execute when clk goes from 0 to 1 or reset_n goes from 1 to 0
always @(posedge clk or negedge reset_n) begin
    timer <= timer + 1; // Increment timer each clock cycle
    // If reset is asserted (active low), go to RED_STATE
    if (!reset_n) begin
        state <= RED_STATE; // Initialize to RED_STATE on reset
        timer <= 0; // Reset timer on reset
    end else begin
        // State machine
        case (state)
            RED_STATE: begin    
                // Only transition to GREEN_STATE after 50 clock cycles
                // Here we set timer to 49 because we start counting from 0
                // So when timer reaches 49, it means 50 cycles have passed
                if (timer == 49) begin    
                state <= GREEN_STATE; // From RED to GREEN
                timer <= 0; // Reset timer on state change
                end
            end
            GREEN_STATE: begin    
                if (timer == 49) begin    
                    state <= YELLOW_STATE; // From GREEN to YELLOW
                    timer <= 0; // Reset timer on state change
                end
            end 
            YELLOW_STATE: begin 
                // The yellow light lasts for a shorter duration
                // Here we set timer to 9 for a 10-cycle duration
                // Because we start counting from 0, reaching 9 means 10 cycles have passed
                if (timer == 9) begin
                    state <= RED_STATE; // From YELLOW to RED
                    timer <= 0; // Reset timer on state change
                end
            end
            default: state <= RED_STATE; // Default case (should not occur)
        endcase

    end
end

// Combinational logic: Output logic based on current state
// The outputs are determined by the current state
// Only one light is on at a time
// The "assign" statements create continuous assignments
// This means the outputs will always reflect the current state
assign red = (state == RED_STATE); // Red light is on in RED_STATE
assign green = (state == GREEN_STATE); // Green light is on in GREEN_STATE
assign yellow = (state == YELLOW_STATE); // Yellow light is on in YELLOW_STATE

endmodule

traffic_light/tb_traffic_light.v
module tb_traffic_light;
    // The "reg" keyword is used for signals that we will drive in the testbench
    // This means we can assign values to them in the testbench
    reg clk;
    reg reset_n;
    // The "wire" keyword is used for signals that are driven by the DUT (Device Under Test)
    // This means we cannot assign values to them in the testbench
    // They will get their values from the traffic_light module
    wire red;
    wire yellow;
    wire green;

    // Instantiate our traffic_light module (DUT - Device Under Test)
    // We connect the signals defined above to the traffic_light ports
    // "uut" stands for "Unit Under Test"
    // The dot notation connects the module ports to the testbench signals
    traffic_light uut (
        .clk(clk),
        .reset_n(reset_n),
        .red(red),
        .yellow(yellow),
        .green(green)
    );

    // 1. Clock generator (This simulates the board oscillator)
    always begin
        clk = 0;
        #5; // Wait 5 time units
        clk = 1;
        #5; // Wait another 5 time units
    end

    always @(posedge red) begin
        $display("[Time %0t]: RED light is ON", $time);
    end

    always @(posedge yellow) begin
        $display("[Time %0t]: YELLOW light is ON", $time);
    end

    always @(posedge green) begin
        $display("[Time %0t]: GREEN light is ON", $time);
    end

    initial begin 
        $dumpfile("waves.vcd"); // Output file name
        $dumpvars(0, tb_traffic_light); // Save all variables from this module

        $display("Starting traffic light simulation...");
        // Initialize signals
        clk = 0;
        reset_n = 0; // Start with reset asserted
        #15;          // Wait 15 time units
        reset_n = 1; // Release reset
        // Run the simulation for a certain period
        #2000;        // Let it run for 2000 time units
        $display("End of traffic light simulation.");
        $finish; // End simulation
    end
endmodule

traffic_light/waves.vcd
$date
	Tue Jan 13 16:47:51 2026
$end
$version
	Icarus Verilog
$end
$timescale
	1s
$end
$scope module tb_traffic_light $end
$var wire 1 ! yellow $end
$var wire 1 " red $end
$var wire 1 # green $end
$var reg 1 $ clk $end
$var reg 1 % reset_n $end
$scope module uut $end
$var wire 1 $ clk $end
$var wire 1 % reset_n $end
$var wire 1 ! yellow $end
$var wire 1 " red $end
$var wire 1 # green $end
$var parameter 2 & GREEN_STATE $end
$var parameter 2 ' RED_STATE $end
$var parameter 2 ( YELLOW_STATE $end
$var reg 2 ) state [1:0] $end
$var reg 6 * timer [5:0] $end
$upscope $end
$upscope $end
$enddefinitions $end
$comment Show the parameter values. $end
$dumpall
b10 (
b0 '
b1 &
$end
#0
$dumpvars
b0 *
b0 )
0%
0$
0#
1"
0!
$end
#5
b0 *
1$
#10
0$
#15
b1 *
1$
1%
#20
0$
#25
b10 *
1$
#30
0$
#35
b11 *
1$
#40
0$
#45
b100 *
1$
#50
0$
#55
b101 *
1$
#60
0$
#65
b110 *
1$
#70
0$
#75
b111 *
1$
#80
0$
#85
b1000 *
1$
#90
0$
#95
b1001 *
1$
#100
0$
#105
b1010 *
1$
#110
0$
#115
b1011 *
1$
#120
0$
#125
b1100 *
1$
#130
0$
#135
b1101 *
1$
#140
0$
#145
b1110 *
1$
#150
0$
#155
b1111 *
1$
#160
0$
#165
b10000 *
1$
#170
0$
#175
b10001 *
1$
#180
0$
#185
b10010 *
1$
#190
0$
#195
b10011 *
1$
#200
0$
#205
b10100 *
1$
#210
0$
#215
b10101 *
1$
#220
0$
#225
b10110 *
1$
#230
0$
#235
b10111 *
1$
#240
0$
#245
b11000 *
1$
#250
0$
#255
b11001 *
1$
#260
0$
#265
b11010 *
1$
#270
0$
#275
b11011 *
1$
#280
0$
#285
b11100 *
1$
#290
0$
#295
b11101 *
1$
#300
0$
#305
b11110 *
1$
#310
0$
#315
b11111 *
1$
#320
0$
#325
b100000 *
1$
#330
0$
#335
b100001 *
1$
#340
0$
#345
b100010 *
1$
#350
0$
#355
b100011 *
1$
#360
0$
#365
b100100 *
1$
#370
0$
#375
b100101 *
1$
#380
0$
#385
b100110 *
1$
#390
0$
#395
b100111 *
1$
#400
0$
#405
b101000 *
1$
#410
0$
#415
b101001 *
1$
#420
0$
#425
b101010 *
1$
#430
0$
#435
b101011 *
1$
#440
0$
#445
b101100 *
1$
#450
0$
#455
b101101 *
1$
#460
0$
#465
b101110 *
1$
#470
0$
#475
b101111 *
1$
#480
0$
#485
b110000 *
1$
#490
0$
#495
b110001 *
1$
#500
0$
#505
0"
1#
b1 )
b0 *
1$
#510
0$
#515
b1 *
1$
#520
0$
#525
b10 *
1$
#530
0$
#535
b11 *
1$
#540
0$
#545
b100 *
1$
#550
0$
#555
b101 *
1$
#560
0$
#565
b110 *
1$
#570
0$
#575
b111 *
1$
#580
0$
#585
b1000 *
1$
#590
0$
#595
b1001 *
1$
#600
0$
#605
b1010 *
1$
#610
0$
#615
b1011 *
1$
#620
0$
#625
b1100 *
1$
#630
0$
#635
b1101 *
1$
#640
0$
#645
b1110 *
1$
#650
0$
#655
b1111 *
1$
#660
0$
#665
b10000 *
1$
#670
0$
#675
b10001 *
1$
#680
0$
#685
b10010 *
1$
#690
0$
#695
b10011 *
1$
#700
0$
#705
b10100 *
1$
#710
0$
#715
b10101 *
1$
#720
0$
#725
b10110 *
1$
#730
0$
#735
b10111 *
1$
#740
0$
#745
b11000 *
1$
#750
0$
#755
b11001 *
1$
#760
0$
#765
b11010 *
1$
#770
0$
#775
b11011 *
1$
#780
0$
#785
b11100 *
1$
#790
0$
#795
b11101 *
1$
#800
0$
#805
b11110 *
1$
#810
0$
#815
b11111 *
1$
#820
0$
#825
b100000 *
1$
#830
0$
#835
b100001 *
1$
#840
0$
#845
b100010 *
1$
#850
0$
#855
b100011 *
1$
#860
0$
#865
b100100 *
1$
#870
0$
#875
b100101 *
1$
#880
0$
#885
b100110 *
1$
#890
0$
#895
b100111 *
1$
#900
0$
#905
b101000 *
1$
#910
0$
#915
b101001 *
1$
#920
0$
#925
b101010 *
1$
#930
0$
#935
b101011 *
1$
#940
0$
#945
b101100 *
1$
#950
0$
#955
b101101 *
1$
#960
0$
#965
b101110 *
1$
#970
0$
#975
b101111 *
1$
#980
0$
#985
b110000 *
1$
#990
0$
#995
b110001 *
1$
#1000
0$
#1005
0#
1!
b10 )
b0 *
1$
#1010
0$
#1015
b1 *
1$
#1020
0$
#1025
b10 *
1$
#1030
0$
#1035
b11 *
1$
#1040
0$
#1045
b100 *
1$
#1050
0$
#1055
b101 *
1$
#1060
0$
#1065
b110 *
1$
#1070
0$
#1075
b111 *
1$
#1080
0$
#1085
b1000 *
1$
#1090
0$
#1095
b1001 *
1$
#1100
0$
#1105
1"
0!
b0 )
b0 *
1$
#1110
0$
#1115
b1 *
1$
#1120
0$
#1125
b10 *
1$
#1130
0$
#1135
b11 *
1$
#1140
0$
#1145
b100 *
1$
#1150
0$
#1155
b101 *
1$
#1160
0$
#1165
b110 *
1$
#1170
0$
#1175
b111 *
1$
#1180
0$
#1185
b1000 *
1$
#1190
0$
#1195
b1001 *
1$
#1200
0$
#1205
b1010 *
1$
#1210
0$
#1215
b1011 *
1$
#1220
0$
#1225
b1100 *
1$
#1230
0$
#1235
b1101 *
1$
#1240
0$
#1245
b1110 *
1$
#1250
0$
#1255
b1111 *
1$
#1260
0$
#1265
b10000 *
1$
#1270
0$
#1275
b10001 *
1$
#1280
0$
#1285
b10010 *
1$
#1290
0$
#1295
b10011 *
1$
#1300
0$
#1305
b10100 *
1$
#1310
0$
#1315
b10101 *
1$
#1320
0$
#1325
b10110 *
1$
#1330
0$
#1335
b10111 *
1$
#1340
0$
#1345
b11000 *
1$
#1350
0$
#1355
b11001 *
1$
#1360
0$
#1365
b11010 *
1$
#1370
0$
#1375
b11011 *
1$
#1380
0$
#1385
b11100 *
1$
#1390
0$
#1395
b11101 *
1$
#1400
0$
#1405
b11110 *
1$
#1410
0$
#1415
b11111 *
1$
#1420
0$
#1425
b100000 *
1$
#1430
0$
#1435
b100001 *
1$
#1440
0$
#1445
b100010 *
1$
#1450
0$
#1455
b100011 *
1$
#1460
0$
#1465
b100100 *
1$
#1470
0$
#1475
b100101 *
1$
#1480
0$
#1485
b100110 *
1$
#1490
0$
#1495
b100111 *
1$
#1500
0$
#1505
b101000 *
1$
#1510
0$
#1515
b101001 *
1$
#1520
0$
#1525
b101010 *
1$
#1530
0$
#1535
b101011 *
1$
#1540
0$
#1545
b101100 *
1$
#1550
0$
#1555
b101101 *
1$
#1560
0$
#1565
b101110 *
1$
#1570
0$
#1575
b101111 *
1$
#1580
0$
#1585
b110000 *
1$
#1590
0$
#1595
b110001 *
1$
#1600
0$
#1605
0"
1#
b1 )
b0 *
1$
#1610
0$
#1615
b1 *
1$
#1620
0$
#1625
b10 *
1$
#1630
0$
#1635
b11 *
1$
#1640
0$
#1645
b100 *
1$
#1650
0$
#1655
b101 *
1$
#1660
0$
#1665
b110 *
1$
#1670
0$
#1675
b111 *
1$
#1680
0$
#1685
b1000 *
1$
#1690
0$
#1695
b1001 *
1$
#1700
0$
#1705
b1010 *
1$
#1710
0$
#1715
b1011 *
1$
#1720
0$
#1725
b1100 *
1$
#1730
0$
#1735
b1101 *
1$
#1740
0$
#1745
b1110 *
1$
#1750
0$
#1755
b1111 *
1$
#1760
0$
#1765
b10000 *
1$
#1770
0$
#1775
b10001 *
1$
#1780
0$
#1785
b10010 *
1$
#1790
0$
#1795
b10011 *
1$
#1800
0$
#1805
b10100 *
1$
#1810
0$
#1815
b10101 *
1$
#1820
0$
#1825
b10110 *
1$
#1830
0$
#1835
b10111 *
1$
#1840
0$
#1845
b11000 *
1$
#1850
0$
#1855
b11001 *
1$
#1860
0$
#1865
b11010 *
1$
#1870
0$
#1875
b11011 *
1$
#1880
0$
#1885
b11100 *
1$
#1890
0$
#1895
b11101 *
1$
#1900
0$
#1905
b11110 *
1$
#1910
0$
#1915
b11111 *
1$
#1920
0$
#1925
b100000 *
1$
#1930
0$
#1935
b100001 *
1$
#1940
0$
#1945
b100010 *
1$
#1950
0$
#1955
b100011 *
1$
#1960
0$
#1965
b100100 *
1$
#1970
0$
#1975
b100101 *
1$
#1980
0$
#1985
b100110 *
1$
#1990
0$
#1995
b100111 *
1$
#2000
0$
#2005
b101000 *
1$
#2010
0$
#2015
b101001 *
1$
